contiv_sdk/__init__.py
contiv_sdk-0.0.4.dist-info/DESCRIPTION.rst
contiv_sdk-0.0.4.dist-info/METADATA
contiv_sdk-0.0.4.dist-info/RECORD
contiv_sdk-0.0.4.dist-info/WHEEL
contiv_sdk-0.0.4.dist-info/metadata.json
contiv_sdk-0.0.4.dist-info/top_level.txt
