Metadata-Version: 2.0
Name: contiv-sdk
Version: 0.0.4
Summary: contiv-python-sdk of SOFTWAY4IoT
Home-page: https://github.com/sw4iot/contiv-python-sdk
Author: SOFTWAY4IoT
Author-email: softway4iot@gmail.com
License: Apache Software License
Keywords: contiv-sdk
Platform: UNKNOWN
Classifier: Development Status :: 3 - Alpha
Classifier: License :: OSI Approved :: Apache Software License
Classifier: Intended Audience :: Developers
Classifier: Natural Language :: English
Classifier: Operating System :: OS Independent
Classifier: Programming Language :: Python :: 2.7
Classifier: Programming Language :: Python :: 3.4
Classifier: Programming Language :: Python :: 3.5
Requires-Dist: requests (>=2.20.0)
Requires-Dist: urllib3 (>=1.23)
